.gitignore
README.rst
setup.py
collective/__init__.py
collective.autosaveform.egg-info/PKG-INFO
collective.autosaveform.egg-info/SOURCES.txt
collective.autosaveform.egg-info/dependency_links.txt
collective.autosaveform.egg-info/entry_points.txt
collective.autosaveform.egg-info/namespace_packages.txt
collective.autosaveform.egg-info/not-zip-safe
collective.autosaveform.egg-info/paster_plugins.txt
collective.autosaveform.egg-info/requires.txt
collective.autosaveform.egg-info/top_level.txt
collective/autosaveform/__init__.py
collective/autosaveform/browser.py
collective/autosaveform/config.py
collective/autosaveform/configure.zcml
collective/autosaveform/tool.py
collective/autosaveform/profiles/default/jsregistry.xml
collective/autosaveform/profiles/default/metadata.xml
collective/autosaveform/profiles/default/skins.xml
collective/autosaveform/profiles/default/toolset.xml
collective/autosaveform/skins/autosaveform/autosave_sample.pt
collective/autosaveform/skins/autosaveform/jquery.autosaveforms.js
collective/autosaveform/tests/__init__.py
collective/autosaveform/tests/base.py
collective/autosaveform/tests/browser.rst
collective/autosaveform/tests/test_browser.py
collective/autosaveform/tests/test_tool.py
collective/autosaveform/tests/tool.rst
docs/HISTORY.txt
docs/INSTALL.txt
docs/LICENSE.GPL
docs/LICENSE.txt