Metadata-Version: 1.0
Name: collective.autosaveform
Version: 0.2
Summary: Utilities to auto save forms while user fills them
Home-page: http://svn.plone.org/svn/collective/
Author: UNKNOWN
Author-email: UNKNOWN
License: GPL
Platform: UNKNOWN
Classifier: Framework :: Plone
Classifier: Programming Language :: Python
